django_haystack_panel-0.2.1.dist-info/DESCRIPTION.rst
django_haystack_panel-0.2.1.dist-info/METADATA
django_haystack_panel-0.2.1.dist-info/pydist.json
django_haystack_panel-0.2.1.dist-info/RECORD
django_haystack_panel-0.2.1.dist-info/top_level.txt
django_haystack_panel-0.2.1.dist-info/WHEEL
haystack_panel/__init__.py
haystack_panel/panel.py
haystack_panel/tests.py
haystack_panel/templates/haystack_panel/haystack_panel.html
