Metadata-Version: 2.0
Name: django-haystack-panel
Version: 0.2.1
Summary: A Django Debug Toolbar panel for Haystack
Home-page: http://github.com/streeter/django-haystack-panel
Author: Chris Streeter
Author-email: chris@chrisstreeter.com
License: MIT
Platform: UNKNOWN
Classifier: Development Status :: 5 - Production/Stable
Classifier: Framework :: Django
Classifier: Intended Audience :: Developers
Classifier: License :: OSI Approved :: MIT License
Classifier: Operating System :: OS Independent
Classifier: Programming Language :: Python
Classifier: Programming Language :: Python :: 2.5
Classifier: Programming Language :: Python :: 2.6
Classifier: Programming Language :: Python :: 2.7
Classifier: Programming Language :: Python :: 3.3
Requires-Dist: django-debug-toolbar (>=1.0)
